ansys/mechanical/stubs/__init__.py
ansys/mechanical/stubs/v242/__init__.py
ansys/mechanical/stubs/v242/Ansys/__init__.py
ansys/mechanical/stubs/v242/Ansys/ACT/__init__.py
ansys/mechanical/stubs/v242/Ansys/ACT/Automation/__init__.py
ansys/mechanical/stubs/v242/Ansys/ACT/Automation/Mechanical/__init__.py
ansys/mechanical/stubs/v242/Ansys/ACT/Automation/Mechanical/AdditiveManufacturing/__init__.py
ansys/mechanical/stubs/v242/Ansys/ACT/Automation/Mechanical/AnalysisSettings/__init__.py
ansys/mechanical/stubs/v242/Ansys/ACT/Automation/Mechanical/BoundaryConditions/__init__.py
ansys/mechanical/stubs/v242/Ansys/ACT/Automation/Mechanical/CondensedParts/__init__.py
ansys/mechanical/stubs/v242/Ansys/ACT/Automation/Mechanical/Connections/__init__.py
ansys/mechanical/stubs/v242/Ansys/ACT/Automation/Mechanical/ConstructionLines/__init__.py
ansys/mechanical/stubs/v242/Ansys/ACT/Automation/Mechanical/FE/__init__.py
ansys/mechanical/stubs/v242/Ansys/ACT/Automation/Mechanical/FE/ABAQUS/__init__.py
ansys/mechanical/stubs/v242/Ansys/ACT/Automation/Mechanical/FE/CDB/__init__.py
ansys/mechanical/stubs/v242/Ansys/ACT/Automation/Mechanical/FE/NASTRAN/__init__.py
ansys/mechanical/stubs/v242/Ansys/ACT/Automation/Mechanical/ImportedLoads/__init__.py
ansys/mechanical/stubs/v242/Ansys/ACT/Automation/Mechanical/MeshControls/__init__.py
ansys/mechanical/stubs/v242/Ansys/ACT/Automation/Mechanical/Results/__init__.py
ansys/mechanical/stubs/v242/Ansys/ACT/Automation/Mechanical/Results/AcousticResults/__init__.py
ansys/mechanical/stubs/v242/Ansys/ACT/Automation/Mechanical/Results/BeamResults/__init__.py
ansys/mechanical/stubs/v242/Ansys/ACT/Automation/Mechanical/Results/BeamToolResults/__init__.py
ansys/mechanical/stubs/v242/Ansys/ACT/Automation/Mechanical/Results/BoltToolResults/__init__.py
ansys/mechanical/stubs/v242/Ansys/ACT/Automation/Mechanical/Results/CompositeFailureResults/__init__.py
ansys/mechanical/stubs/v242/Ansys/ACT/Automation/Mechanical/Results/ContactToolResults/__init__.py
ansys_mechanical_stubs-2024.2.0.dist-info/LICENSE
ansys_mechanical_stubs-2024.2.0.dist-info/WHEEL
ansys_mechanical_stubs-2024.2.0.dist-info/METADATA
ansys_mechanical_stubs-2024.2.0.dist-info/RECORD
