Metadata-Version: 2.3
Name: ansys-mechanical-stubs
Version: 2024.2.0
Summary: Mechanical scripting API stubs for PyMechanical.
Author-email: "ANSYS, Inc." <pyansys.core@ansys.com>
Maintainer-email: "ANSYS, Inc." <pyansys.core@ansys.com>
Requires-Python: >=3.10,<4
Classifier: Development Status :: 4 - Beta
Classifier: Intended Audience :: Science/Research
Classifier: Topic :: Scientific/Engineering :: Information Analysis
Classifier: License :: OSI Approved :: MIT License
Classifier: Operating System :: OS Independent
Classifier: Programming Language :: Python :: 3.10
Classifier: Programming Language :: Python :: 3.11
Classifier: Programming Language :: Python :: 3.12
Requires-Dist: ansys-pythonnet==3.1.0rc3 ; extra == "build"
Requires-Dist: ansys-sphinx-theme[autoapi]==1.0.11 ; extra == "doc"
Requires-Dist: Sphinx==7.3.7 ; extra == "doc"
Requires-Dist: sphinx-copybutton==0.5.2 ; extra == "doc"
Requires-Dist: sphinx-notfound-page==1.0.2 ; extra == "doc"
Requires-Dist: sphinx-design==0.6.1 ; extra == "doc"
Requires-Dist: sphinx-jinja==2.0.2 ; extra == "doc"
Requires-Dist: autodoc_pydantic==2.0.1 ; extra == "doc"
Requires-Dist: jupyter_sphinx==0.5.3 ; extra == "doc"
Requires-Dist: numpydoc==1.6.0 ; extra == "doc"
Requires-Dist: sphinx-autodoc-typehints==1.25.3 ; extra == "doc"
Requires-Dist: sphinxcontrib-globalsubs==0.1.1 ; extra == "doc"
Requires-Dist: sphinxcontrib-httpdomain==1.8.1 ; extra == "doc"
Requires-Dist: sphinx-copybutton==0.5.2 ; extra == "doc"
Requires-Dist: sphinx_design==0.6.1 ; extra == "doc"
Requires-Dist: sphinx-markdown-builder==0.6.6 ; extra == "doc"
Requires-Dist: sphinxnotes-strike==1.2.1 ; extra == "doc"
Requires-Dist: pytest==8.3.3 ; extra == "tests"
Requires-Dist: pytest-cov==5.0.0 ; extra == "tests"
Project-URL: Documentation, https://scripting.mechanical.docs.pyansys.com
Project-URL: Homepage, https://github.com/ansys/mechanical-stubs
Project-URL: Source, https://github.com/ansys/mechanical-stubs/
Project-URL: Tracker, https://github.com/ansys/mechanical-stubs/issues
Provides-Extra: build
Provides-Extra: doc
Provides-Extra: tests
